guillotina_dbusers/__init__.py
guillotina_dbusers/install.py
guillotina_dbusers/interfaces.py
guillotina_dbusers/subscribers.py
guillotina_dbusers/users.py
guillotina_dbusers/content/__init__.py
guillotina_dbusers/content/groups.py
guillotina_dbusers/content/users.py
guillotina_dbusers/services/__init__.py
guillotina_dbusers/services/groups.py
guillotina_dbusers/services/users.py
guillotina_dbusers/tests/conftest.py
guillotina_dbusers/tests/test_api.py
guillotina_dbusers/tests/test_setup.py
guillotina_dbusers-2.0.2.dist-info/METADATA
guillotina_dbusers-2.0.2.dist-info/RECORD
guillotina_dbusers-2.0.2.dist-info/WHEEL
guillotina_dbusers-2.0.2.dist-info/top_level.txt
guillotina_dbusers-2.0.2.dist-info/zip-safe
