Metadata-Version: 2.1
Name: guillotina-dbusers
Version: 2.0.2
Summary: guillotina addon to provide users that are stored in the database
Home-page: https://pypi.python.org/pypi/guillotina_dbusers
Author: Nathan Van Gheem
Author-email: vangheem@gmail.com
License: GPL version 3
Keywords: async,guillotina,users,auth
Platform: UNKNOWN
Classifier: Programming Language :: Python :: 3.6
Classifier: Topic :: Software Development :: Libraries :: Python Modules
Provides-Extra: test
Requires-Dist: setuptools
Requires-Dist: guillotina (>=4.2.1)
Provides-Extra: test
Requires-Dist: pytest; extra == 'test'
Requires-Dist: requests; extra == 'test'
